federal_register/client.py
federal_register/fields.py
federal_register-0.0.1.dist-info/LICENSE
federal_register-0.0.1.dist-info/METADATA
federal_register-0.0.1.dist-info/WHEEL
federal_register-0.0.1.dist-info/top_level.txt
federal_register-0.0.1.dist-info/RECORD
